__init__.py
ufns.py
ufns-0.0.1.dist-info/LICENCE
ufns-0.0.1.dist-info/METADATA
ufns-0.0.1.dist-info/WHEEL
ufns-0.0.1.dist-info/top_level.txt
ufns-0.0.1.dist-info/RECORD
