Metadata-Version: 2.2
Name: ufns
Version: 0.0.1
Summary: Utility Functions
Author-email: Liam Leonard <liamleonard@outlook.ie>
Project-URL: Homepage, https://github.com/liam-leonard/ufns
Project-URL: Issues, https://github.com/liam-leonard/ufns/issues
Classifier: Programming Language :: Python :: 3
Classifier: License :: OSI Approved :: MIT License
Classifier: Operating System :: OS Independent
Requires-Python: >=3.7
License-File: LICENCE
